rndc_python/__init__.py
rndc_python/cli.py
rndc_python/config.py
rndc_python/enums.py
rndc_python/exceptions.py
rndc_python/py.typed
rndc_python/rndc_client.py
rndc_python/rndc_config.py
rndc_python/rndc_protocol.py
rndc_python-0.1.1.dist-info/METADATA
rndc_python-0.1.1.dist-info/WHEEL
rndc_python-0.1.1.dist-info/entry_points.txt
rndc_python-0.1.1.dist-info/licenses/LICENSE
rndc_python-0.1.1.dist-info/RECORD
