Metadata-Version: 2.4
Name: rndc-python
Version: 0.1.1
Summary: Python client for ISC BIND's RNDC
Project-URL: Homepage, https://github.com/davidgroves/rndc-python
Project-URL: Repository, https://github.com/davidgroves/rndc-python
Project-URL: Issues, https://github.com/davidgroves/rndc-python/issues
Author-email: David Groves <dave@fibrecat.org>
License-Expression: MIT
License-File: LICENSE
Keywords: bind,dns,named,rndc,tsig
Classifier: Development Status :: 4 - Beta
Classifier: Intended Audience :: Developers
Classifier: Intended Audience :: System Administrators
Classifier: License :: OSI Approved :: MIT License
Classifier: Operating System :: OS Independent
Classifier: Programming Language :: Python :: 3
Classifier: Programming Language :: Python :: 3.10
Classifier: Programming Language :: Python :: 3.11
Classifier: Programming Language :: Python :: 3.12
Classifier: Programming Language :: Python :: 3.13
Classifier: Programming Language :: Python :: 3.14
Classifier: Topic :: Internet :: Name Service (DNS)
Classifier: Topic :: System :: Systems Administration
Classifier: Typing :: Typed
Requires-Python: >=3.10
Requires-Dist: click>=8.1.0
Requires-Dist: dnspython>=2.6.1
Requires-Dist: python-dotenv>=1.0.1
Provides-Extra: dev
Requires-Dist: pre-commit>=4.0.0; extra == 'dev'
Requires-Dist: ruff>=0.8.0; extra == 'dev'
Requires-Dist: ty>=0.0.3; extra == 'dev'
Provides-Extra: test
Requires-Dist: pytest-cov>=6.0.0; extra == 'test'
Requires-Dist: pytest-mock>=3.14.0; extra == 'test'
Requires-Dist: pytest>=8.3.0; extra == 'test'
Requires-Dist: testcontainers>=4.9.0; extra == 'test'
